README.md
setup.py
stylelens_search/__init__.py
stylelens_search/api_client.py
stylelens_search/configuration.py
stylelens_search/rest.py
stylelens_search.egg-info/PKG-INFO
stylelens_search.egg-info/SOURCES.txt
stylelens_search.egg-info/dependency_links.txt
stylelens_search.egg-info/requires.txt
stylelens_search.egg-info/top_level.txt
stylelens_search/apis/__init__.py
stylelens_search/apis/search_api.py
stylelens_search/models/__init__.py
stylelens_search/models/image.py
stylelens_search/models/image_search_response.py
stylelens_search/models/image_search_response_data.py
stylelens_search/models/images_array.py
test/__init__.py
test/test_image.py
test/test_image_search_response.py
test/test_image_search_response_data.py
test/test_images_array.py
test/test_search_api.py