Metadata-Version: 1.0
Name: stylelens-search
Version: 1.0.1
Summary: stylelens-search
Home-page: UNKNOWN
Author: UNKNOWN
Author-email: devops@bluehack.net
License: UNKNOWN
Keywords: Swagger,stylelens-search
Platform: UNKNOWN
